AsiacellX/__init__.py
AsiacellX/client.py
AsiacellX/utils/__init__.py
AsiacellX/utils/headers.py
AsiacellX/utils/helpers.py
asiacellx-1.1.1.dist-info/METADATA
asiacellx-1.1.1.dist-info/WHEEL
asiacellx-1.1.1.dist-info/top_level.txt
asiacellx-1.1.1.dist-info/RECORD
