Metadata-Version: 2.4
Name: AsiacellX
Version: 1.1.1
Summary: A Python library for interacting with Asiacell's website and mobile application.
Author: ZOOM
Keywords: Python,Asiacell,API,Iraq,zainiraq,sms
Requires-Python: >=3.6
Dynamic: author
Dynamic: description
Dynamic: description-content-type
Dynamic: keywords
Dynamic: requires-python
Dynamic: summary
